{
  "id": "11-change-password",
  "type": "page",
  "name": "修改密码",
  "product": {
    "summary": "已登录用户修改密码的页面：旧密码 + 新密码 + 确认新密码",
    "ref": "product-analysis/modules/M5-user-auth.md#c2-业务规则",
    "fromModules": [
      "M5"
    ],
    "rules": [
      "旧密码必填且校验通过才能继续",
      "新密码 8-20 位 + 含字母+数字，不能与旧密码相同",
      "修改成功后所有设备强制重新登录（除当前设备）",
      "失败 ≥3 次锁定 30 分钟，需走找回密码",
      "操作记入安全日志，并通过强制类通知告知账号本人"
    ]
  },
  "implementation": {
    "nodeId": null,
    "status": "pending"
  },
  "interaction": {
    "summary": "旧密码+新密码+确认 3 字段；失败 3 次锁 30min 强制走找回密码；成功后其他设备下线",
    "ref": "interaction-design/pages/11-change-password.md",
    "states": [
      "idle",
      "inputting",
      "submitting",
      "success",
      "error:wrong-old",
      "error:locked",
      "error:weak-new",
      "error:same-as-old",
      "error:mismatch"
    ],
    "operations": [
      {
        "op": "返回",
        "triggerNodePath": "app-bar/back-btn"
      },
      {
        "op": "输入旧密码",
        "triggerNodePath": "form-card/old-password-input"
      },
      {
        "op": "输入新密码",
        "triggerNodePath": "form-card/new-password-input"
      },
      {
        "op": "输入确认密码",
        "triggerNodePath": "form-card/confirm-password-input"
      },
      {
        "op": "点击保存",
        "triggerNodePath": "submit-btn"
      },
      {
        "op": "跳到找回密码（锁定后强制）",
        "triggerNodePath": "forgot-link"
      }
    ]
  },
  "_updatedAt": "2026-05-28T05:05:21.327Z"
}
