{
  "id": "upload-video-btn",
  "type": "element",
  "name": "дёҠдј жүӢжҢҒи§Ҷйў‘",
  "interaction": {
    "summary": "clickвҶ’е”Өиө·и§Ҷйў‘жӢҚж‘„/зӣёеҶҢ",
    "ref": "interaction-design/pages/00-auth-face.md#ж“ҚдҪңжё…еҚ•:5",
    "trigger": "click",
    "condition": "{{ pageState in [\"error:max-retries\",\"error:no-match\"] }}",
    "flows": {
      "success": {
        "summary": "жҸҗдәӨи§Ҷйў‘вҶ’иҪ¬дәәе·Ҙе®Ўж ё",
        "ref": "interaction-design/pages/00-auth-face.md#ж“ҚдҪңжё…еҚ•:5"
      },
      "error": {
        "summary": "и§Ҷйў‘ <5s жҲ– >50MBвҶ’Toast",
        "ref": "interaction-design/pages/00-auth-face.md#й”ҷиҜҜеӨ„зҗҶ"
      }
    },
    "states": [
      "idle",
      "pressing",
      "uploading"
    ]
  },
  "implementation": {
    "nodeId": null,
    "status": "pending"
  }
}
