{
  "id": "withdraw-btn",
  "type": "element",
  "name": "ж’Өеӣһ",
  "interaction": {
    "summary": "clickвҶ’L4 Confirm ж’Өеӣһпјӣд»… pending дё” <1h жҳҫзӨә",
    "ref": "interaction-design/pages/02-greets-sent.md#ж“ҚдҪңжё…еҚ•:5",
    "trigger": "click",
    "flows": {
      "success": {
        "summary": "д№җи§Ӯжӣҙж–°вҶ’withdraw-success",
        "ref": "ж“ҚдҪңжё…еҚ•:5"
      },
      "error": {
        "summary": "already-readвҶ’L4 Modalпјӣи¶…ж—¶вҶ’L4 Modal",
        "ref": "02-greets-sent.md#й”ҷиҜҜеӨ„зҗҶ"
      }
    },
    "states": [
      "idle",
      "pressing",
      "withdrawing"
    ]
  },
  "implementation": {
    "nodeId": null,
    "status": "pending"
  }
}
