{
  "themes": [
    {
      "id": "default",
      "name": "青春治愈",
      "description": "校园地理社交 D6 视觉决策：明亮配色（草莓粉/薄荷绿/奶油黄）+ 圆角 + 手绘插画风图标 + 弹性有机微动效。Light + Dark 双方案。",
      "createdAt": "2026-05-28T04:25:00Z",
      "updatedAt": "2026-05-28T04:25:00Z",

      "intent": {
        "summary": "青春治愈风：草莓粉为主、薄荷绿辅、奶油黄点缀；大圆角、柔和暖白底、手绘 outline 图标、弹性微动效。营造校园年轻、温暖、有惊喜感的氛围。",
        "aesthetics": ["organic", "playful", "hand-drawn"],
        "decoration": "moderate",
        "colorTemperature": "warm",
        "brightness": "both",
        "seedColors": ["#FF6F91", "#6FE2A8", "#FFD777"],
        "audience": "在校大学生（18-24 岁）+ 校友 + 跨校观察者",
        "scenario": "校园地理社交 App（位置动态/捞网/胶囊/跨校漫游）",
        "references": []
      },

      "tokens": {
        "colors": {
          "primary": { "value": "#FF6F91", "description": "草莓粉主色（HSL 346 100% 72%）" },
          "primaryHover": { "value": "#FF89A4", "description": "主色悬浮（亮度 +6%）" },
          "primaryActive": { "value": "#FB406F", "description": "主色按下（亮度 -8%）" },
          "primaryLight": { "value": "#FFE6EC", "description": "主色浅底（亮度 95%）" },
          "secondary": { "value": "#6FE2A8", "description": "薄荷绿辅色（H 146°，分裂互补）" },
          "secondaryHover": { "value": "#88EBB7", "description": "辅色悬浮" },
          "secondaryActive": { "value": "#4ED28E", "description": "辅色按下" },

          "background": { "value": "#FFFAF6", "description": "页面底色：暖白带奶油色调" },
          "surface": { "value": "#FFFFFF", "description": "卡片/列表表面" },
          "surfaceElevated": { "value": "#FFFFFF", "description": "悬浮面（浮动按钮/弹窗）" },
          "overlay": { "value": "rgba(45, 36, 56, 0.45)", "description": "蒙层（带紫调更治愈）" },

          "textPrimary": { "value": "rgba(45, 36, 56, 0.92)", "description": "正文（深紫棕，APCA Lc ~90）" },
          "textSecondary": { "value": "rgba(45, 36, 56, 0.65)", "description": "辅助文字（Lc ~65）" },
          "textTertiary": { "value": "rgba(45, 36, 56, 0.42)", "description": "占位/三级文字（Lc ~45，仅用于 placeholder/timestamp）" },
          "textInverse": { "value": "#FFFFFF", "description": "反色文字（按钮/badge 上）" },

          "border": { "value": "#FFE0E8", "description": "默认边框（淡粉）" },
          "borderLight": { "value": "#F5EDE6", "description": "分割线（奶油浅）" },
          "borderFocus": { "value": "#FF6F91", "description": "聚焦边框 = primary" },

          "success": { "value": "#3FCC93", "description": "成功（薄荷派生）" },
          "warning": { "value": "#FFC74D", "description": "警告（奶油黄派生）" },
          "error": { "value": "#ED5A5A", "description": "错误（柔和红，不刺眼）" },
          "info": { "value": "#57A8F0", "description": "信息（清亮蓝）" },

          "sunshineYellow": { "value": "#FFD777", "description": "点缀色：奶油黄（用于装饰/胶囊高亮/任务卡片）" },
          "campusMint": { "value": "#6FE2A8", "description": "点缀色：薄荷绿（= secondary，用于二级强调）" },
          "creamCream": { "value": "#FFF5E6", "description": "奶油底色变体（任务/胶囊背景）" },
          "lavenderHint": { "value": "#E8DFF5", "description": "极淡薰衣草：胶囊/夜晚场景装饰" }
        },

        "spacing": {
          "2xs": { "value": "2px", "px": 2, "description": "极小（图标内描边）" },
          "xs": { "value": "4px", "px": 4, "description": "超小（图标-文字间隙）" },
          "sm": { "value": "8px", "px": 8, "description": "小（紧凑列表）" },
          "md": { "value": "16px", "px": 16, "description": "中（默认页面横边距）" },
          "lg": { "value": "24px", "px": 24, "description": "大（卡片内边距）" },
          "xl": { "value": "32px", "px": 32, "description": "超大（区块间距）" },
          "2xl": { "value": "48px", "px": 48, "description": "极大（页面节段）" },
          "3xl": { "value": "64px", "px": 64, "description": "巨大（顶部空白/空状态）" }
        },

        "radius": {
          "none": { "value": "0", "description": "无圆角" },
          "sm": { "value": "6px", "description": "小圆角（标签/小按钮）" },
          "md": { "value": "12px", "description": "中圆角（输入框/小卡片）" },
          "lg": { "value": "16px", "description": "大圆角（动态卡片/图片）" },
          "xl": { "value": "24px", "description": "超大圆角（弹窗/底部抽屉）" },
          "2xl": { "value": "32px", "description": "极大圆角（特殊高亮卡片）" },
          "full": { "value": "9999px", "description": "全圆（头像/胶囊按钮/Tab 高亮）" }
        },

        "typography": {
          "display": {
            "fontFamily": "Nunito, \"PingFang SC\", -apple-system, BlinkMacSystemFont, \"Helvetica Neue\", sans-serif",
            "fontSize": "48px", "lineHeight": "1.15", "fontWeight": "800",
            "description": "展示标题（启动页/胶囊解锁）"
          },
          "h1": {
            "fontFamily": "Nunito, \"PingFang SC\", -apple-system, sans-serif",
            "fontSize": "36px", "lineHeight": "1.2", "fontWeight": "700",
            "description": "一级标题（页面主标题）"
          },
          "h2": {
            "fontFamily": "Nunito, \"PingFang SC\", -apple-system, sans-serif",
            "fontSize": "28px", "lineHeight": "1.25", "fontWeight": "700",
            "description": "二级标题（弹窗/区块）"
          },
          "h3": {
            "fontFamily": "Nunito, \"PingFang SC\", -apple-system, sans-serif",
            "fontSize": "22px", "lineHeight": "1.3", "fontWeight": "600",
            "description": "三级标题（卡片标题）"
          },
          "h4": {
            "fontFamily": "Nunito, \"PingFang SC\", -apple-system, sans-serif",
            "fontSize": "18px", "lineHeight": "1.35", "fontWeight": "600",
            "description": "四级标题（列表项主文）"
          },
          "h5": {
            "fontFamily": "Nunito, \"PingFang SC\", -apple-system, sans-serif",
            "fontSize": "16px", "lineHeight": "1.4", "fontWeight": "600",
            "description": "五级标题（小标题）"
          },
          "body-lg": {
            "fontFamily": "Nunito, \"PingFang SC\", -apple-system, sans-serif",
            "fontSize": "16px", "lineHeight": "1.5", "fontWeight": "400",
            "description": "大正文（动态正文/重要描述）"
          },
          "body": {
            "fontFamily": "Nunito, \"PingFang SC\", -apple-system, sans-serif",
            "fontSize": "14px", "lineHeight": "1.5", "fontWeight": "400",
            "description": "正文（默认）"
          },
          "caption": {
            "fontFamily": "Nunito, \"PingFang SC\", -apple-system, sans-serif",
            "fontSize": "12px", "lineHeight": "1.4", "fontWeight": "400",
            "description": "辅助文字（时间/位置/计数）"
          },
          "overline": {
            "fontFamily": "Nunito, \"PingFang SC\", -apple-system, sans-serif",
            "fontSize": "10px", "lineHeight": "1.4", "fontWeight": "600",
            "letterSpacing": "0.06em",
            "description": "上标小字（标签/分组头）"
          }
        },

        "shadows": {
          "sm": { "value": "0 2px 6px rgba(255, 111, 145, 0.08), 0 1px 2px rgba(45, 36, 56, 0.04)", "description": "小阴影（卡片悬浮一点点，主色微调）" },
          "md": { "value": "0 4px 16px rgba(255, 111, 145, 0.10), 0 2px 4px rgba(45, 36, 56, 0.04)", "description": "中阴影（下拉/Toast）" },
          "lg": { "value": "0 8px 28px rgba(255, 111, 145, 0.12), 0 4px 8px rgba(45, 36, 56, 0.05)", "description": "大阴影（浮动按钮/弹窗）" },
          "xl": { "value": "0 16px 48px rgba(255, 111, 145, 0.14), 0 8px 16px rgba(45, 36, 56, 0.06)", "description": "超大阴影（模态/底部抽屉）" }
        },

        "transitions": {
          "fast": { "value": "all 200ms cubic-bezier(0.34, 1.56, 0.64, 1)", "durationMs": 200, "description": "快速弹性（点击/小切换，spring 微回弹）" },
          "normal": { "value": "all 300ms cubic-bezier(0.34, 1.56, 0.64, 1)", "durationMs": 300, "description": "正常弹性（按钮按下/卡片展开）" },
          "slow": { "value": "all 500ms cubic-bezier(0.22, 1, 0.36, 1)", "durationMs": 500, "description": "缓慢出场（页面切换，无回弹）" },
          "page": { "value": "transform 350ms cubic-bezier(0.22, 1, 0.36, 1), opacity 250ms ease-out", "durationMs": 350, "description": "页面级转场（push/modalUp）" }
        },

        "custom": {
          "bottomTabHeight": { "value": "68px", "type": "size", "description": "底部 4 Tab 高度（含安全区）" },
          "topNavHeight": { "value": "44px", "type": "size", "description": "顶部导航栏高度（不含状态栏）" },
          "fabSize": { "value": "56px", "type": "size", "description": "首页发布浮动按钮直径" },
          "avatarMd": { "value": "40px", "type": "size", "description": "默认头像尺寸（列表/会话）" },
          "avatarLg": { "value": "64px", "type": "size", "description": "大头像（个人主页/捞到的人卡片）" }
        }
      },

      "colorSchemes": [
        {
          "id": "light",
          "name": "light",
          "label": "浅色（默认）",
          "overrides": {}
        },
        {
          "id": "dark",
          "name": "dark",
          "label": "深色（V1.x 预留，V1.0 不开放）",
          "overrides": {
            "colors": {
              "background": "#1F1318",
              "surface": "#2A1B22",
              "surfaceElevated": "#382433",
              "overlay": "rgba(0, 0, 0, 0.7)",
              "textPrimary": "rgba(255, 250, 246, 0.92)",
              "textSecondary": "rgba(255, 250, 246, 0.65)",
              "textTertiary": "rgba(255, 250, 246, 0.42)",
              "textInverse": "#2D2438",
              "border": "#4A2F3A",
              "borderLight": "#382433",
              "primaryLight": "#4A1F2C",
              "creamCream": "#3A2A20",
              "lavenderHint": "#3A2F4A"
            },
            "shadows": {
              "sm": "0 2px 6px rgba(0, 0, 0, 0.35)",
              "md": "0 4px 16px rgba(0, 0, 0, 0.45)",
              "lg": "0 8px 28px rgba(0, 0, 0, 0.55)",
              "xl": "0 16px 48px rgba(0, 0, 0, 0.65)"
            }
          }
        }
      ],
      "activeColorSchemeId": "light",

      "decorationRules": {
        "background": { "strategy": "solid" },
        "border": { "strategy": "subtle", "width": "1px" },
        "shadow": { "strategy": "soft" },
        "motion": { "strategy": "spring", "easing": "cubic-bezier(0.34, 1.56, 0.64, 1)" },
        "iconStyle": "outline",
        "cornerStyle": "rounded",
        "textDecoration": {
          "gradientHeading": false,
          "accentUnderline": false
        }
      },

      "iconSpec": {
        "style": "outline",
        "stroke": {
          "width": 2.0,
          "linecap": "round",
          "linejoin": "round",
          "cornerRadius": 2
        },
        "colors": {
          "default": "$token:textSecondary",
          "active": "$token:primary",
          "inactive": "$token:textTertiary",
          "secondary": "$token:primaryLight"
        },
        "sizing": {
          "containerRatio": 0.55,
          "minPadding": 6,
          "strokeCompensation": true
        },
        "variants": {
          "inactive": { "opacity": 0.5, "color": "$token:textTertiary" },
          "active": { "opacity": 1.0, "strokeWidth": 2.3, "color": "$token:primary" },
          "hover": { "opacity": 0.85 },
          "disabled": { "opacity": 0.4, "grayscale": false }
        },
        "consistency": {
          "targetComplexity": "medium",
          "uniformStrokeWidth": true,
          "geometricOnly": false
        }
      },

      "stateSpec": {
        "hover": {
          "backgroundLightnessShift": 5,
          "shadowLevel": "up",
          "scale": 1.03,
          "transition": "$token:transition-fast"
        },
        "active": {
          "backgroundLightnessShift": -5,
          "shadowLevel": "down",
          "scale": 0.97,
          "transition": "$token:transition-fast"
        },
        "focus": {
          "ringColor": "$token:primary",
          "ringWidth": "2px",
          "ringOffset": "2px",
          "animated": true
        },
        "disabled": {
          "opacity": 0.45,
          "removeShadow": true,
          "cursor": "not-allowed",
          "grayscale": false
        },
        "loading": {
          "opacity": 0.85,
          "spinnerColor": "$token:primary",
          "skeleton": true
        }
      }
    }
  ],

  "activeThemeId": "default",
  "customized": true
}
